simpleCPU/src/ram.v
`timescale 1ns/10ps

module ram (
	clk,
	addr,
	DO, // data out
	DI, // data in
	EN, // chip select (enable)
	WE, // write enable
	RE // read enable
	);

parameter AddrSize = 11;
parameter WordSize = 9;

input wire clk;
input wire [AddrSize-1:0] addr;
output reg [WordSize-1:0] DO;
input wire [WordSize-1:0] DI;
input wire EN, WE, RE;

reg [WordSize-1:0] Mem [0:(1<<AddrSize)-1];

always @ (posedge clk)
begin
	if (EN && RE)
		DO <= Mem[addr];
	else
		DO <= {WordSize{1'bx}};
end

initial begin
	$display("Loading ram.");
	$readmemb("ram.mem", Mem);
end

always @ (posedge clk)
	if (EN && WE)
		Mem[addr] <= DI;

always @(WE or RE)
	if (WE && RE)
		$display("Operational error in RamChip: RE and WE both active");
endmodule

simpleCPU/src/rom.v
`timescale 1ns/10ps

module rom (
	clk,
	addr,
	DO, // data out
	EN // enable
	);

parameter AddrSize = 11;
parameter WordSize = 9;

input clk;
input [AddrSize-1:0] addr;
output reg [WordSize-1:0] DO;
reg [WordSize-1:0] r_DO;
input EN;

reg [WordSize-1:0] Mem [0:(1<<AddrSize)-1];

always @ (posedge clk)
	r_DO <= DO;

always @ (posedge clk)
begin
	if (EN)
		DO <= Mem[addr];
	else
		DO <= {WordSize{1'b0}};
end

initial begin
	$display("Loading rom.");
	$readmemb("rom.mem", Mem);
end

endmodule

simpleCPU/cpu.v
`timescale 1ns/10ps

// Instruction set (9b):
// LD  | V V V V V V V V 1 | R0 <- V
// MOV | A A A B B B 0 0 0 | A <- B
// CMP | A A A B B B 0 1 0 | CMP A and B
// JE  | V V V V V 0 1 1 0 | PC <- V if FE=1
// JMP | V V V V V 0 1 0 0 | PC <- V
// ADD | 0 0 0 0 0 1 0 0 0 | R0 <- R0 + R1
// AND | 0 0 0 0 0 1 0 0 1 | R0 <- R0 & R1
// OR  | 0 0 0 0 0 1 0 1 1 | R0 <- R0 | R1
// NOT | 0 0 0 0 0 1 0 1 0 | R0 <- ! R0
// XOR | 0 0 0 0 0 1 1 0 0 | R0 <- R0 ^ R1
// NOP | 0 0 0 0 0 1 1 0 1 | 

module cpu
	#(
	parameter g_ROM_WIDTH = 11,
	parameter g_ROM_ADDR = 9,
	parameter g_RAM_WIDTH = 11,
	parameter g_RAM_ADDR = 9
	)
	(
	input i_clk,
	input i_rst,

	output reg o_rom_en,
	output wire [g_ROM_ADDR-1:0] o_rom_addr,
	input [g_ROM_WIDTH-1:0] i_rom_data,

	output reg o_ram_en,
	output reg o_ram_we,
	output reg o_ram_re,
	output reg [g_RAM_ADDR-1:0] o_ram_addr,
	output reg [g_RAM_WIDTH-1:0] o_ram_data,
	input [g_RAM_WIDTH-1:0] i_ram_data
	);

	// Registers
	reg [15:0] r_pc; // program counter
	reg [7:0] r_gpr[7:0]; // 8 general purpose registers

	reg [g_ROM_ADDR-1:0] r_rom_addr;

	assign o_rom_addr = r_rom_addr;

	always @ (posedge i_clk or i_rst)
	begin
		if (i_rst == 1'b1)
		begin
			r_rom_addr <= 0;
		end
		else
		begin
			r_rom_addr <= r_rom_addr + 1;
			o_ram_en <= 1'b1;
			o_rom_en <= 1'b1;
		end
	end

endmodule

simpleCPU/top_wrapper.v
`include "cpu.v"
`include "ram.v"
`include "rom.v"

`timescale 1ns/10ps

module top_wrapper
	(
	 input wire [0:0] i_clk,
	 output wire [7:0] o_led,
	 input wire [4:0] i_btn,
	 //input wire [0:0] i_rx,
	 //output wire [0:0] o_tx,
	 input wire [7:0] i_sw
	);
	
	wire w_rom_en;
	wire [10:0] w_rom_addr;
	wire [8:0] w_rom_data;
	wire w_ram_en;
	wire w_ram_we;
	wire w_ram_re;
	wire [10:0] w_ram_addr;
	wire [8:0] w_ram_data_o;
	wire [8:0] w_ram_data_i;

	reg [7:0] r_led = 8'b10011001;

	assign o_led = r_led;

	cpu #(
		.g_ROM_WIDTH(9),
		.g_ROM_ADDR(11),
		.g_RAM_WIDTH(9),
		.g_RAM_ADDR(11)
		)
		CPU_INST
		(
		.i_clk(i_clk),
		.i_rst(i_btn[0]),
		.o_rom_en(w_rom_en),
		.o_rom_addr(w_rom_addr),
		.i_rom_data(w_rom_data),
		.o_ram_en(w_ram_en),
		.o_ram_we(w_ram_we),
		.o_ram_re(w_ram_re),
		.o_ram_addr(w_ram_addr),
		.o_ram_data(w_ram_data_o),
		.i_ram_data(w_ram_data_i)
		);

	rom #(
		.AddrSize(11),
		.WordSize(9)
		)
		ROM_INST
		(
		.clk(i_clk),
		.addr(w_rom_addr),
		.DO(w_rom_data),
		.EN(w_rom_en)
		);

	ram #(
		.AddrSize(11),
		.WordSize(9)
		)
		RAM_INST
		(
		.clk(i_clk),
		.addr(w_ram_addr),
		.DO(w_ram_data_i),
		.DI(w_ram_data_o),
		.EN(w_ram_en),
		.WE(w_ram_we),
		.RE(w_ram_re)
		);

endmodule

simpleCPU/top_wrapper_tb.v
`include "top_wrapper.v"

`timescale 1ns/10ps

module top_wrapper_tb ();

	parameter c_CLOCK_PERIOD_NS = 100;

	reg r_clk = 0;
	wire [7:0] w_led;
	reg [4:0] r_btn = 0;
	reg [7:0] r_sw = 0;

	always
	#(c_CLOCK_PERIOD_NS/2) r_clk <= !r_clk;

	top_wrapper WRAPPER_INST
		(
		.i_clk(r_clk),
		.o_led(w_led),
		.i_btn(r_btn),
		//.i_rx(),
		//.o_tx(),
		.i_sw(r_sw)
		);

	initial
	begin
		$dumpfile("mydump.vcd");
		$dumpvars(0, WRAPPER_INST);
		$display("Start simulation");
		#1000;
		r_btn <= 5'b00001;
		#10000;
		$finish;
	end

endmodule

simpleCPU/mydump.vcd
$date
	Sun Apr 21 16:49:08 2019
$end
$version
	Icarus Verilog
$end
$timescale
	10ps
$end
$scope module top_wrapper_tb $end
$scope module WRAPPER_INST $end
$var wire 5 ! i_btn [4:0] $end
$var wire 1 " i_clk $end
$var wire 8 # i_sw [7:0] $end
$var wire 8 $ o_led [7:0] $end
$var wire 1 % w_rom_en $end
$var wire 9 & w_rom_data [8:0] $end
$var wire 11 ' w_rom_addr [10:0] $end
$var wire 1 ( w_ram_we $end
$var wire 1 ) w_ram_re $end
$var wire 1 * w_ram_en $end
$var wire 9 + w_ram_data_o [8:0] $end
$var wire 9 , w_ram_data_i [8:0] $end
$var wire 11 - w_ram_addr [10:0] $end
$var reg 8 . r_led [7:0] $end
$scope module CPU_INST $end
$var wire 1 " i_clk $end
$var wire 1 / i_rst $end
$var wire 11 0 o_rom_addr [10:0] $end
$var wire 9 1 i_rom_data [8:0] $end
$var wire 9 2 i_ram_data [8:0] $end
$var reg 11 3 o_ram_addr [10:0] $end
$var reg 9 4 o_ram_data [8:0] $end
$var reg 1 * o_ram_en $end
$var reg 1 ) o_ram_re $end
$var reg 1 ( o_ram_we $end
$var reg 1 % o_rom_en $end
$var reg 11 5 r_rom_addr [10:0] $end
$upscope $end
$scope module RAM_INST $end
$var wire 9 6 DI [8:0] $end
$var wire 1 * EN $end
$var wire 1 ) RE $end
$var wire 1 ( WE $end
$var wire 11 7 addr [10:0] $end
$var wire 1 " clk $end
$var reg 9 8 DO [8:0] $end
$upscope $end
$scope module ROM_INST $end
$var wire 1 % EN $end
$var wire 11 9 addr [10:0] $end
$var wire 1 " clk $end
$var reg 9 : DO [8:0] $end
$var reg 9 ; r_DO [8:0] $end
$upscope $end
$upscope $end
$upscope $end
$enddefinitions $end
#0
$dumpvars
bx ;
bx :
b0 9
bx 8
bx 7
bx 6
b0 5
bx 4
bx 3
bx 2
bx 1
b0 0
1/
b10011001 .
bx -
bx ,
bx +
x*
x)
x(
b0 '
bx &
x%
b10011001 $
b0 #
0"
b1 !
$end
#5000
bz ;
bz ,
bz 2
bz 8
1"
#10000
0"
#15000
bz &
bz 1
bz :
1"
#20000
0"
#25000
1"
#30000
0"
#35000
1"
#40000
0"
#45000
1"
#50000
0"
#55000
1"
#60000
0"
#65000
1"
#70000
0"
#75000
1"
#80000
0"
#85000
1"
#90000
0"
#95000
1"
#100000
1%
1*
b1 '
b1 0
b1 9
b1 5
0/
0"
b0 !
#105000
b10 '
b10 0
b10 9
b10 5
b10 ;
1"
#110000
0"
#115000
b11 '
b11 0
b11 9
b11 5
b11 ;
b10 &
b10 1
b10 :
1"
#120000
0"
#125000
b100 '
b100 0
b100 9
b100 5
b11 &
b11 1
b11 :
b100 ;
1"
#130000
0"
#135000
b101 '
b101 0
b101 9
b101 5
b101 ;
b100 &
b100 1
b100 :
1"
#140000
0"
#145000
b110 '
b110 0
b110 9
b110 5
b101 &
b101 1
b101 :
b110 ;
1"
#150000
0"
#155000
b111 '
b111 0
b111 9
b111 5
b111 ;
b110 &
b110 1
b110 :
1"
#160000
0"
#165000
b1000 '
b1000 0
b1000 9
b1000 5
b111 &
b111 1
b111 :
b1000 ;
1"
#170000
0"
#175000
b1001 '
b1001 0
b1001 9
b1001 5
b1001 ;
b1000 &
b1000 1
b1000 :
1"
#180000
0"
#185000
b1010 '
b1010 0
b1010 9
b1010 5
b1001 &
b1001 1
b1001 :
b0 ;
1"
#190000
0"
#195000
b1011 '
b1011 0
b1011 9
b1011 5
b0 &
b0 1
b0 :
1"
#200000
0"
#205000
b1100 '
b1100 0
b1100 9
b1100 5
1"
#210000
0"
#215000
b1101 '
b1101 0
b1101 9
b1101 5
1"
#220000
0"
#225000
b1110 '
b1110 0
b1110 9
b1110 5
1"
#230000
0"
#235000
b1111 '
b1111 0
b1111 9
b1111 5
1"
#240000
0"
#245000
b10000 '
b10000 0
b10000 9
b10000 5
1"
#250000
0"
#255000
b10001 '
b10001 0
b10001 9
b10001 5
1"
#260000
0"
#265000
b10010 '
b10010 0
b10010 9
b10010 5
1"
#270000
0"
#275000
b10011 '
b10011 0
b10011 9
b10011 5
1"
#280000
0"
#285000
b10100 '
b10100 0
b10100 9
b10100 5
1"
#290000
0"
#295000
b10101 '
b10101 0
b10101 9
b10101 5
1"
#300000
0"
#305000
b10110 '
b10110 0
b10110 9
b10110 5
1"
#310000
0"
#315000
b10111 '
b10111 0
b10111 9
b10111 5
1"
#320000
0"
#325000
b11000 '
b11000 0
b11000 9
b11000 5
1"
#330000
0"
#335000
b11001 '
b11001 0
b11001 9
b11001 5
1"
#340000
0"
#345000
b11010 '
b11010 0
b11010 9
b11010 5
1"
#350000
0"
#355000
b11011 '
b11011 0
b11011 9
b11011 5
1"
#360000
0"
#365000
b11100 '
b11100 0
b11100 9
b11100 5
1"
#370000
0"
#375000
b11101 '
b11101 0
b11101 9
b11101 5
1"
#380000
0"
#385000
b11110 '
b11110 0
b11110 9
b11110 5
1"
#390000
0"
#395000
b11111 '
b11111 0
b11111 9
b11111 5
1"
#400000
0"
#405000
b100000 '
b100000 0
b100000 9
b100000 5
1"
#410000
0"
#415000
b100001 '
b100001 0
b100001 9
b100001 5
1"
#420000
0"
#425000
b100010 '
b100010 0
b100010 9
b100010 5
1"
#430000
0"
#435000
b100011 '
b100011 0
b100011 9
b100011 5
1"
#440000
0"
#445000
b100100 '
b100100 0
b100100 9
b100100 5
1"
#450000
0"
#455000
b100101 '
b100101 0
b100101 9
b100101 5
1"
#460000
0"
#465000
b100110 '
b100110 0
b100110 9
b100110 5
1"
#470000
0"
#475000
b100111 '
b100111 0
b100111 9
b100111 5
1"
#480000
0"
#485000
b101000 '
b101000 0
b101000 9
b101000 5
1"
#490000
0"
#495000
b101001 '
b101001 0
b101001 9
b101001 5
1"
#500000
0"
#505000
b101010 '
b101010 0
b101010 9
b101010 5
1"
#510000
0"
#515000
b101011 '
b101011 0
b101011 9
b101011 5
1"
#520000
0"
#525000
b101100 '
b101100 0
b101100 9
b101100 5
1"
#530000
0"
#535000
b101101 '
b101101 0
b101101 9
b101101 5
1"
#540000
0"
#545000
b101110 '
b101110 0
b101110 9
b101110 5
1"
#550000
0"
#555000
b101111 '
b101111 0
b101111 9
b101111 5
1"
#560000
0"
#565000
b110000 '
b110000 0
b110000 9
b110000 5
1"
#570000
0"
#575000
b110001 '
b110001 0
b110001 9
b110001 5
1"
#580000
0"
#585000
b110010 '
b110010 0
b110010 9
b110010 5
1"
#590000
0"
#595000
b110011 '
b110011 0
b110011 9
b110011 5
1"
#600000
0"
#605000
b110100 '
b110100 0
b110100 9
b110100 5
1"
#610000
0"
#615000
b110101 '
b110101 0
b110101 9
b110101 5
1"
#620000
0"
#625000
b110110 '
b110110 0
b110110 9
b110110 5
1"
#630000
0"
#635000
b110111 '
b110111 0
b110111 9
b110111 5
1"
#640000
0"
#645000
b111000 '
b111000 0
b111000 9
b111000 5
1"
#650000
0"
#655000
b111001 '
b111001 0
b111001 9
b111001 5
1"
#660000
0"
#665000
b111010 '
b111010 0
b111010 9
b111010 5
1"
#670000
0"
#675000
b111011 '
b111011 0
b111011 9
b111011 5
1"
#680000
0"
#685000
b111100 '
b111100 0
b111100 9
b111100 5
1"
#690000
0"
#695000
b111101 '
b111101 0
b111101 9
b111101 5
1"
#700000
0"
#705000
b111110 '
b111110 0
b111110 9
b111110 5
1"
#710000
0"
#715000
b111111 '
b111111 0
b111111 9
b111111 5
1"
#720000
0"
#725000
b1000000 '
b1000000 0
b1000000 9
b1000000 5
1"
#730000
0"
#735000
b1000001 '
b1000001 0
b1000001 9
b1000001 5
1"
#740000
0"
#745000
b1000010 '
b1000010 0
b1000010 9
b1000010 5
1"
#750000
0"
#755000
b1000011 '
b1000011 0
b1000011 9
b1000011 5
1"
#760000
0"
#765000
b1000100 '
b1000100 0
b1000100 9
b1000100 5
1"
#770000
0"
#775000
b1000101 '
b1000101 0
b1000101 9
b1000101 5
1"
#780000
0"
#785000
b1000110 '
b1000110 0
b1000110 9
b1000110 5
1"
#790000
0"
#795000
b1000111 '
b1000111 0
b1000111 9
b1000111 5
1"
#800000
0"
#805000
b1001000 '
b1001000 0
b1001000 9
b1001000 5
1"
#810000
0"
#815000
b1001001 '
b1001001 0
b1001001 9
b1001001 5
1"
#820000
0"
#825000
b1001010 '
b1001010 0
b1001010 9
b1001010 5
1"
#830000
0"
#835000
b1001011 '
b1001011 0
b1001011 9
b1001011 5
1"
#840000
0"
#845000
b1001100 '
b1001100 0
b1001100 9
b1001100 5
1"
#850000
0"
#855000
b1001101 '
b1001101 0
b1001101 9
b1001101 5
1"
#860000
0"
#865000
b1001110 '
b1001110 0
b1001110 9
b1001110 5
1"
#870000
0"
#875000
b1001111 '
b1001111 0
b1001111 9
b1001111 5
1"
#880000
0"
#885000
b1010000 '
b1010000 0
b1010000 9
b1010000 5
1"
#890000
0"
#895000
b1010001 '
b1010001 0
b1010001 9
b1010001 5
1"
#900000
0"
#905000
b1010010 '
b1010010 0
b1010010 9
b1010010 5
1"
#910000
0"
#915000
b1010011 '
b1010011 0
b1010011 9
b1010011 5
1"
#920000
0"
#925000
b1010100 '
b1010100 0
b1010100 9
b1010100 5
1"
#930000
0"
#935000
b1010101 '
b1010101 0
b1010101 9
b1010101 5
1"
#940000
0"
#945000
b1010110 '
b1010110 0
b1010110 9
b1010110 5
1"
#950000
0"
#955000
b1010111 '
b1010111 0
b1010111 9
b1010111 5
1"
#960000
0"
#965000
b1011000 '
b1011000 0
b1011000 9
b1011000 5
1"
#970000
0"
#975000
b1011001 '
b1011001 0
b1011001 9
b1011001 5
1"
#980000
0"
#985000
b1011010 '
b1011010 0
b1011010 9
b1011010 5
1"
#990000
0"
#995000
b1011011 '
b1011011 0
b1011011 9
b1011011 5
1"
#1000000
0"
#1005000
b1011100 '
b1011100 0
b1011100 9
b1011100 5
1"
#1010000
0"
#1015000
b1011101 '
b1011101 0
b1011101 9
b1011101 5
1"
#1020000
0"
#1025000
b1011110 '
b1011110 0
b1011110 9
b1011110 5
1"
#1030000
0"
#1035000
b1011111 '
b1011111 0
b1011111 9
b1011111 5
1"
#1040000
0"
#1045000
b1100000 '
b1100000 0
b1100000 9
b1100000 5
1"
#1050000
0"
#1055000
b1100001 '
b1100001 0
b1100001 9
b1100001 5
1"
#1060000
0"
#1065000
b1100010 '
b1100010 0
b1100010 9
b1100010 5
1"
#1070000
0"
#1075000
b1100011 '
b1100011 0
b1100011 9
b1100011 5
1"
#1080000
0"
#1085000
b1100100 '
b1100100 0
b1100100 9
b1100100 5
1"
#1090000
0"
#1095000
b1100101 '
b1100101 0
b1100101 9
b1100101 5
1"
